{
  "$schema": "https://developer.microsoft.com/json-schemas/fabric/item/report/definition/visualContainer/2.2.0/schema.json",
  "name": "3e2306dc59c360dbc05c",
  "position": {
    "x": 9.576106492102225,
    "y": 0,
    "z": 0,
    "height": 111.32223797068838,
    "width": 209.4773295147362
  },
  "visual": {
    "visualType": "card",
    "query": {
      "queryState": {
        "Values": {
          "projections": [
            {
              "field": {
                "Measure": {
                  "Expression": {
                    "SourceRef": {
                      "Entity": "Sheet1"
                    }
                  },
                  "Property": "Campaign Count"
                }
              },
              "queryRef": "Sheet1.Campaign Count",
              "nativeQueryRef": "Campaign Count"
            }
          ]
        }
      },
      "sortDefinition": {
        "sort": [
          {
            "field": {
              "Measure": {
                "Expression": {
                  "SourceRef": {
                    "Entity": "Sheet1"
                  }
                },
                "Property": "Campaign Count"
              }
            },
            "direction": "Descending"
          }
        ],
        "isDefaultSort": true
      }
    },
    "drillFilterOtherVisuals": true
  }
}