{
  "version": "1.1.0",
  "diagrams": [
    {
      "ordinal": 0,
      "scrollPosition": {
        "x": 525.08990638800765,
        "y": 0
      },
      "nodes": [
        {
          "location": {
            "x": 1420,
            "y": 0
          },
          "nodeIndex": "Sheet1",
          "nodeLineageTag": "1e529b7d-468f-4750-8508-2acc2deff55b",
          "size": {
            "height": 300,
            "width": 234
          },
          "zIndex": 5
        },
        {
          "location": {
            "x": 284,
            "y": 86
          },
          "nodeIndex": "Dim Company",
          "nodeLineageTag": "a8791149-e775-47db-9bba-f4280349e8af",
          "size": {
            "height": 128,
            "width": 234
          },
          "zIndex": 1
        },
        {
          "location": {
            "x": 568,
            "y": 86
          },
          "nodeIndex": "Dim Customer Segment",
          "nodeLineageTag": "368c90cc-f8f7-4b4d-8c18-1c68fb85ad31",
          "size": {
            "height": 128,
            "width": 234
          },
          "zIndex": 2
        },
        {
          "location": {
            "x": 852,
            "y": 86
          },
          "nodeIndex": "Dim Language",
          "nodeLineageTag": "52080910-118a-4a1d-b2b4-a5a413ca51c1",
          "size": {
            "height": 128,
            "width": 234
          },
          "zIndex": 3
        },
        {
          "location": {
            "x": 1136,
            "y": 86
          },
          "nodeIndex": "Dim Location",
          "nodeLineageTag": "be526cec-531e-42b3-b105-2ae2b5b10878",
          "size": {
            "height": 128,
            "width": 234
          },
          "zIndex": 4
        },
        {
          "location": {
            "x": 1704,
            "y": 50
          },
          "nodeIndex": "Date",
          "size": {
            "height": 200,
            "width": 234
          },
          "zIndex": 7
        },
        {
          "location": {
            "x": 15.801011485520831,
            "y": 84.4198988514479
          },
          "nodeIndex": "Dim Channel_Used",
          "nodeLineageTag": "c4663325-420c-4c76-ae9e-4eb36cfcfcfd",
          "size": {
            "height": 128,
            "width": 234
          },
          "zIndex": 6
        }
      ],
      "name": "All tables",
      "zoomValue": 89.192590520569908,
      "pinKeyFieldsToTop": false,
      "showExtraHeaderInfo": false,
      "hideKeyFieldsWhenCollapsed": false,
      "tablesLocked": false
    }
  ],
  "selectedDiagram": "All tables",
  "defaultDiagram": "All tables"
}